Workbook

Sheet Regras
A1: Regras para cadastrar produtos e contas
A2: Resumo do modelo e de como usar esta planilha.
A4: COMO USAR
A5: 1. Editar | B5: Preencha as celulas em azul (fundo amarelo) nas abas Produtos e Produtos_Cosif. Ha linhas em branco no fim de cada tabela.
A6: 2. Conferir | B6: A coluna Validacao deve mostrar OK em todas as linhas antes de gerar o SQL.
A7: 3. Gerar SQL | B7: Copie a coluna "SQL para o console do H2" da aba Produtos e depois a da aba Produtos_Cosif, nesta ordem.
A8: 4. Executar | B8: Cole no console do H2 (http://localhost:8080/h2-console) e clique em Run. Depois aperte F5 na tela do sistema.
A10: REGRAS DO MODELO
A11: Ordem | B11: Primeiro o PRODUTO, depois as contas dele (PRODUTO_COSIF). A chave estrangeira nao deixa ligar conta a produto inexistente.
A12: COD_PRODUTO | B12: CHAR(4): exatamente 4 caracteres, ex.: 0006. Nao pode repetir.
A13: DES_PRODUTO | B13: VARCHAR(30): ate 30 caracteres. E o texto do combo Produto.
A14: COD_COSIF | B14: CHAR(11): 11 digitos, sem pontos.
A15: COD_CLASSIFICACAO | B15: CHAR(6): ate 6 caracteres. Aparece no combo como COD_COSIF - (CLASSIFICACAO).
A16: STA_STATUS | B16: CHAR(1): A = ativo, I = inativo.
A17: Chave de PRODUTO_COSIF | B17: O PAR (COD_PRODUTO, COD_COSIF) nao pode repetir. A mesma conta pode servir a varios produtos.
A18: Produto sem conta | B18: Aparece no combo Produto, mas o combo Cosif fica vazio: nao da para lancar nada nele.
A19: MERGE ... KEY | B19: Comando do H2 que insere ou atualiza pela chave. O SQL gerado pode ser executado mais de uma vez sem erro.
A21: PERMANENCIA
A22: Banco em memoria | B22: O que for incluido pelo console SOME ao reiniciar o back-end. As linhas com Origem = data.sql voltam sozinhas.
A23: Deixar permanente | B23: Acrescente os comandos ao final de backend/src/main/resources/data.sql, trocando "MERGE INTO ... KEY (...)" por "INSERT INTO".
A24: Atencao aos testes | B24: O RepositoriosJpaTest espera 4 produtos e 2 contas para o produto 0001 no data.sql. Se acrescentar ao data.sql, ajuste esses numeros.
A26: LEGENDA DE CORES
A27: Azul, fundo amarelo | B27: Dado digitado (editavel).
A28: Preto | B28: Formula calculada nesta aba (nao editar).
A29: Verde | B29: Formula que busca dados em outra aba (nao editar).
A31: Observacao | B31: Os codigos COSIF e as classificacoes sao ILUSTRATIVOS, criados para o desafio. Nao sao contas reais do plano do Banco Central.

Sheet Produtos
A1: Produtos
A2: Celulas em azul com fundo amarelo = dados que voce edita. Colunas em preto = formulas (nao editar).
A4: Código do Produto | B4: Descrição (DES_PRODUTO) | C4: Status | D4: Origem | E4: Qtd de contas COSIF | F4: Validação | G4: SQL para o console do H2
A5: 0001 | B5: CDB Pos-Fixado | C5: A | D5: data.sql | E5: =IF(A5="","",COUNTIF(Produtos_Cosif!$A:$A,A5)) -> 3 | F5: =IF(A5="","",IF(AND(LEN(A5)=4,LEN(B5)<=30,LEN(B5)>0,OR(C5="A",C5="I")),IF(E5=0,"Sem conta: combo Cosif vazio","OK"),"Verificar tamanhos/status")) -> OK | G5: =IF(A5="","","MERGE INTO PRODUTO (COD_PRODUTO, DES_PRODUTO, STA_STATUS) KEY (COD_PRODUTO) VALUES ('"&A5&"', '"&B5&"', '"&C5&"');") -> MERGE INTO PRODUTO (COD_PRODUTO, DES_PRODUTO, STA_STATUS) KEY (COD_PRODUTO) VALUES ('0001', 'CDB Pos-Fixado', 'A');
A6: 0002 | B6: LCI | C6: A | D6: data.sql | E6: =IF(A6="","",COUNTIF(Produtos_Cosif!$A:$A,A6)) -> 1 | F6: =IF(A6="","",IF(AND(LEN(A6)=4,LEN(B6)<=30,LEN(B6)>0,OR(C6="A",C6="I")),IF(E6=0,"Sem conta: combo Cosif vazio","OK"),"Verificar tamanhos/status")) -> OK | G6: =IF(A6="","","MERGE INTO PRODUTO (COD_PRODUTO, DES_PRODUTO, STA_STATUS) KEY (COD_PRODUTO) VALUES ('"&A6&"', '"&B6&"', '"&C6&"');") -> MERGE INTO PRODUTO (COD_PRODUTO, DES_PRODUTO, STA_STATUS) KEY (COD_PRODUTO) VALUES ('0002', 'LCI', 'A');
A7: 0003 | B7: Emprestimo Consignado | C7: A | D7: data.sql | E7: =IF(A7="","",COUNTIF(Produtos_Cosif!$A:$A,A7)) -> 2 | F7: =IF(A7="","",IF(AND(LEN(A7)=4,LEN(B7)<=30,LEN(B7)>0,OR(C7="A",C7="I")),IF(E7=0,"Sem conta: combo Cosif vazio","OK"),"Verificar tamanhos/status")) -> OK | G7: =IF(A7="","","MERGE INTO PRODUTO (COD_PRODUTO, DES_PRODUTO, STA_STATUS) KEY (COD_PRODUTO) VALUES ('"&A7&"', '"&B7&"', '"&C7&"');") -> MERGE INTO PRODUTO (COD_PRODUTO, DES_PRODUTO, STA_STATUS) KEY (COD_PRODUTO) VALUES ('0003', 'Emprestimo Consignado', 'A');
A8: 0004 | B8: Cambio Pronto | C8: A | D8: data.sql | E8: =IF(A8="","",COUNTIF(Produtos_Cosif!$A:$A,A8)) -> 2 | F8: =IF(A8="","",IF(AND(LEN(A8)=4,LEN(B8)<=30,LEN(B8)>0,OR(C8="A",C8="I")),IF(E8=0,"Sem conta: combo Cosif vazio","OK"),"Verificar tamanhos/status")) -> OK | G8: =IF(A8="","","MERGE INTO PRODUTO (COD_PRODUTO, DES_PRODUTO, STA_STATUS) KEY (COD_PRODUTO) VALUES ('"&A8&"', '"&B8&"', '"&C8&"');") -> MERGE INTO PRODUTO (COD_PRODUTO, DES_PRODUTO, STA_STATUS) KEY (COD_PRODUTO) VALUES ('0004', 'Cambio Pronto', 'A');
A9: 0006 | B9: Poupanca | C9: A | D9: script 07 | E9: =IF(A9="","",COUNTIF(Produtos_Cosif!$A:$A,A9)) -> 2 | F9: =IF(A9="","",IF(AND(LEN(A9)=4,LEN(B9)<=30,LEN(B9)>0,OR(C9="A",C9="I")),IF(E9=0,"Sem conta: combo Cosif vazio","OK"),"Verificar tamanhos/status")) -> OK | G9: =IF(A9="","","MERGE INTO PRODUTO (COD_PRODUTO, DES_PRODUTO, STA_STATUS) KEY (COD_PRODUTO) VALUES ('"&A9&"', '"&B9&"', '"&C9&"');") -> MERGE INTO PRODUTO (COD_PRODUTO, DES_PRODUTO, STA_STATUS) KEY (COD_PRODUTO) VALUES ('0006', 'Poupanca', 'A');
A10: 0007 | B10: Conta Corrente | C10: A | D10: script 07 | E10: =IF(A10="","",COUNTIF(Produtos_Cosif!$A:$A,A10)) -> 2 | F10: =IF(A10="","",IF(AND(LEN(A10)=4,LEN(B10)<=30,LEN(B10)>0,OR(C10="A",C10="I")),IF(E10=0,"Sem conta: combo Cosif vazio","OK"),"Verificar tamanhos/status")) -> OK | G10: =IF(A10="","","MERGE INTO PRODUTO (COD_PRODUTO, DES_PRODUTO, STA_STATUS) KEY (COD_PRODUTO) VALUES ('"&A10&"', '"&B10&"', '"&C10&"');") -> MERGE INTO PRODUTO (COD_PRODUTO, DES_PRODUTO, STA_STATUS) KEY (COD_PRODUTO) VALUES ('0007', 'Conta Corrente', 'A');
A11: 0008 | B11: Credito Pessoal | C11: A | D11: script 07 | E11: =IF(A11="","",COUNTIF(Produtos_Cosif!$A:$A,A11)) -> 3 | F11: =IF(A11="","",IF(AND(LEN(A11)=4,LEN(B11)<=30,LEN(B11)>0,OR(C11="A",C11="I")),IF(E11=0,"Sem conta: combo Cosif vazio","OK"),"Verificar tamanhos/status")) -> OK | G11: =IF(A11="","","MERGE INTO PRODUTO (COD_PRODUTO, DES_PRODUTO, STA_STATUS) KEY (COD_PRODUTO) VALUES ('"&A11&"', '"&B11&"', '"&C11&"');") -> MERGE INTO PRODUTO (COD_PRODUTO, DES_PRODUTO, STA_STATUS) KEY (COD_PRODUTO) VALUES ('0008', 'Credito Pessoal', 'A');
A12: 0009 | B12: Financiamento Imobiliario | C12: A | D12: script 07 | E12: =IF(A12="","",COUNTIF(Produtos_Cosif!$A:$A,A12)) -> 2 | F12: =IF(A12="","",IF(AND(LEN(A12)=4,LEN(B12)<=30,LEN(B12)>0,OR(C12="A",C12="I")),IF(E12=0,"Sem conta: combo Cosif vazio","OK"),"Verificar tamanhos/status")) -> OK | G12: =IF(A12="","","MERGE INTO PRODUTO (COD_PRODUTO, DES_PRODUTO, STA_STATUS) KEY (COD_PRODUTO) VALUES ('"&A12&"', '"&B12&"', '"&C12&"');") -> MERGE INTO PRODUTO (COD_PRODUTO, DES_PRODUTO, STA_STATUS) KEY (COD_PRODUTO) VALUES ('0009', 'Financiamento Imobiliario', 'A');
A13: 0010 | B13: Fundo de Investimento | C13: A | D13: script 07 | E13: =IF(A13="","",COUNTIF(Produtos_Cosif!$A:$A,A13)) -> 1 | F13: =IF(A13="","",IF(AND(LEN(A13)=4,LEN(B13)<=30,LEN(B13)>0,OR(C13="A",C13="I")),IF(E13=0,"Sem conta: combo Cosif vazio","OK"),"Verificar tamanhos/status")) -> OK | G13: =IF(A13="","","MERGE INTO PRODUTO (COD_PRODUTO, DES_PRODUTO, STA_STATUS) KEY (COD_PRODUTO) VALUES ('"&A13&"', '"&B13&"', '"&C13&"');") -> MERGE INTO PRODUTO (COD_PRODUTO, DES_PRODUTO, STA_STATUS) KEY (COD_PRODUTO) VALUES ('0010', 'Fundo de Investimento', 'A');
E14: =IF(A14="","",COUNTIF(Produtos_Cosif!$A:$A,A14)) | F14: =IF(A14="","",IF(AND(LEN(A14)=4,LEN(B14)<=30,LEN(B14)>0,OR(C14="A",C14="I")),IF(E14=0,"Sem conta: combo Cosif vazio","OK"),"Verificar tamanhos/status")) | G14: =IF(A14="","","MERGE INTO PRODUTO (COD_PRODUTO, DES_PRODUTO, STA_STATUS) KEY (COD_PRODUTO) VALUES ('"&A14&"', '"&B14&"', '"&C14&"');")
E15: =IF(A15="","",COUNTIF(Produtos_Cosif!$A:$A,A15)) | F15: =IF(A15="","",IF(AND(LEN(A15)=4,LEN(B15)<=30,LEN(B15)>0,OR(C15="A",C15="I")),IF(E15=0,"Sem conta: combo Cosif vazio","OK"),"Verificar tamanhos/status")) | G15: =IF(A15="","","MERGE INTO PRODUTO (COD_PRODUTO, DES_PRODUTO, STA_STATUS) KEY (COD_PRODUTO) VALUES ('"&A15&"', '"&B15&"', '"&C15&"');")
E16: =IF(A16="","",COUNTIF(Produtos_Cosif!$A:$A,A16)) | F16: =IF(A16="","",IF(AND(LEN(A16)=4,LEN(B16)<=30,LEN(B16)>0,OR(C16="A",C16="I")),IF(E16=0,"Sem conta: combo Cosif vazio","OK"),"Verificar tamanhos/status")) | G16: =IF(A16="","","MERGE INTO PRODUTO (COD_PRODUTO, DES_PRODUTO, STA_STATUS) KEY (COD_PRODUTO) VALUES ('"&A16&"', '"&B16&"', '"&C16&"');")
E17: =IF(A17="","",COUNTIF(Produtos_Cosif!$A:$A,A17)) | F17: =IF(A17="","",IF(AND(LEN(A17)=4,LEN(B17)<=30,LEN(B17)>0,OR(C17="A",C17="I")),IF(E17=0,"Sem conta: combo Cosif vazio","OK"),"Verificar tamanhos/status")) | G17: =IF(A17="","","MERGE INTO PRODUTO (COD_PRODUTO, DES_PRODUTO, STA_STATUS) KEY (COD_PRODUTO) VALUES ('"&A17&"', '"&B17&"', '"&C17&"');")
E18: =IF(A18="","",COUNTIF(Produtos_Cosif!$A:$A,A18)) | F18: =IF(A18="","",IF(AND(LEN(A18)=4,LEN(B18)<=30,LEN(B18)>0,OR(C18="A",C18="I")),IF(E18=0,"Sem conta: combo Cosif vazio","OK"),"Verificar tamanhos/status")) | G18: =IF(A18="","","MERGE INTO PRODUTO (COD_PRODUTO, DES_PRODUTO, STA_STATUS) KEY (COD_PRODUTO) VALUES ('"&A18&"', '"&B18&"', '"&C18&"');")
E19: =IF(A19="","",COUNTIF(Produtos_Cosif!$A:$A,A19)) | F19: =IF(A19="","",IF(AND(LEN(A19)=4,LEN(B19)<=30,LEN(B19)>0,OR(C19="A",C19="I")),IF(E19=0,"Sem conta: combo Cosif vazio","OK"),"Verificar tamanhos/status")) | G19: =IF(A19="","","MERGE INTO PRODUTO (COD_PRODUTO, DES_PRODUTO, STA_STATUS) KEY (COD_PRODUTO) VALUES ('"&A19&"', '"&B19&"', '"&C19&"');")
E20: =IF(A20="","",COUNTIF(Produtos_Cosif!$A:$A,A20)) | F20: =IF(A20="","",IF(AND(LEN(A20)=4,LEN(B20)<=30,LEN(B20)>0,OR(C20="A",C20="I")),IF(E20=0,"Sem conta: combo Cosif vazio","OK"),"Verificar tamanhos/status")) | G20: =IF(A20="","","MERGE INTO PRODUTO (COD_PRODUTO, DES_PRODUTO, STA_STATUS) KEY (COD_PRODUTO) VALUES ('"&A20&"', '"&B20&"', '"&C20&"');")
E21: =IF(A21="","",COUNTIF(Produtos_Cosif!$A:$A,A21)) | F21: =IF(A21="","",IF(AND(LEN(A21)=4,LEN(B21)<=30,LEN(B21)>0,OR(C21="A",C21="I")),IF(E21=0,"Sem conta: combo Cosif vazio","OK"),"Verificar tamanhos/status")) | G21: =IF(A21="","","MERGE INTO PRODUTO (COD_PRODUTO, DES_PRODUTO, STA_STATUS) KEY (COD_PRODUTO) VALUES ('"&A21&"', '"&B21&"', '"&C21&"');")
E22: =IF(A22="","",COUNTIF(Produtos_Cosif!$A:$A,A22)) | F22: =IF(A22="","",IF(AND(LEN(A22)=4,LEN(B22)<=30,LEN(B22)>0,OR(C22="A",C22="I")),IF(E22=0,"Sem conta: combo Cosif vazio","OK"),"Verificar tamanhos/status")) | G22: =IF(A22="","","MERGE INTO PRODUTO (COD_PRODUTO, DES_PRODUTO, STA_STATUS) KEY (COD_PRODUTO) VALUES ('"&A22&"', '"&B22&"', '"&C22&"');")
E23: =IF(A23="","",COUNTIF(Produtos_Cosif!$A:$A,A23)) | F23: =IF(A23="","",IF(AND(LEN(A23)=4,LEN(B23)<=30,LEN(B23)>0,OR(C23="A",C23="I")),IF(E23=0,"Sem conta: combo Cosif vazio","OK"),"Verificar tamanhos/status")) | G23: =IF(A23="","","MERGE INTO PRODUTO (COD_PRODUTO, DES_PRODUTO, STA_STATUS) KEY (COD_PRODUTO) VALUES ('"&A23&"', '"&B23&"', '"&C23&"');")

Sheet Produtos_Cosif
A1: Contas COSIF permitidas por produto (PRODUTO_COSIF)
A2: Uma linha por par produto + conta. Edite as celulas em azul; as demais sao formulas.
A4: Código do Produto | B4: COSIF (11 dígitos) | C4: Classificação | D4: Status | E4: Lógica (por que essa conta) | F4: Origem | G4: Produto | H4: Grupo COSIF (1º dígito) | I4: Texto no combo da tela | J4: Conta compartilhada? | K4: Validação | L4: SQL para o console do H2
A5: 0001 | B5: 41510000001 | C5: PASSIV | D5: A | E5: CDB e uma divida do banco com o cliente | F5: data.sql | G5: =IF(A5="","",IFERROR(INDEX(Produtos!$B$5:$B$23,MATCH(A5,Produtos!$A$5:$A$23,0)),"Produto nao cadastrado")) -> CDB Pos-Fixado | H5: =IF(B5="","",IFERROR(VLOOKUP(LEFT(B5,1),Grupos_COSIF!$A$5:$B$12,2,FALSE()),"Outro")) -> Passivo circulante e exigivel a longo prazo | I5: =IF(B5="","",B5&" - ("&TRIM(C5)&")") -> 41510000001 - (PASSIV) | J5: =IF(B5="","",IF(COUNTIF($B$5:$B$37,B5)>1,"Sim","Nao")) -> Nao | K5: =IF(A5="","",IF(G5="Produto nao cadastrado","Cadastre o produto antes",IF(COUNTIFS($A$5:$A$37,A5,$B$5:$B$37,B5)>1,"Par duplicado",IF(AND(LEN(A5)=4,LEN(B5)=11,LEN(C5)<=6,OR(D5="A",D5="I")),"OK","Verificar tamanhos/status")))) -> OK | L5: =IF(A5="","","MERGE INTO PRODUTO_COSIF (COD_PRODUTO, COD_COSIF, COD_CLASSIFICACAO, STA_STATUS) KEY (COD_PRODUTO, COD_COSIF) VALUES ('"&A5&"', '"&B5&"', '"&C5&"', '"&D5&"');") -> MERGE INTO PRODUTO_COSIF (COD_PRODUTO, COD_COSIF, COD_CLASSIFICACAO, STA_STATUS) KEY (COD_PRODUTO, COD_COSIF) VALUES ('0001', '41510000001', 'PASSIV', 'A');
A6: 0001 | B6: 81120000002 | C6: DESPES | D6: A | E6: Juros que o banco paga no CDB | F6: data.sql | G6: =IF(A6="","",IFERROR(INDEX(Produtos!$B$5:$B$23,MATCH(A6,Produtos!$A$5:$A$23,0)),"Produto nao cadastrado")) -> CDB Pos-Fixado | H6: =IF(B6="","",IFERROR(VLOOKUP(LEFT(B6,1),Grupos_COSIF!$A$5:$B$12,2,FALSE()),"Outro")) -> Contas de resultado devedoras (despesas) | I6: =IF(B6="","",B6&" - ("&TRIM(C6)&")") -> 81120000002 - (DESPES) | J6: =IF(B6="","",IF(COUNTIF($B$5:$B$37,B6)>1,"Sim","Nao")) -> Nao | K6: =IF(A6="","",IF(G6="Produto nao cadastrado","Cadastre o produto antes",IF(COUNTIFS($A$5:$A$37,A6,$B$5:$B$37,B6)>1,"Par duplicado",IF(AND(LEN(A6)=4,LEN(B6)=11,LEN(C6)<=6,OR(D6="A",D6="I")),"OK","Verificar tamanhos/status")))) -> OK | L6: =IF(A6="","","MERGE INTO PRODUTO_COSIF (COD_PRODUTO, COD_COSIF, COD_CLASSIFICACAO, STA_STATUS) KEY (COD_PRODUTO, COD_COSIF) VALUES ('"&A6&"', '"&B6&"', '"&C6&"', '"&D6&"');") -> MERGE INTO PRODUTO_COSIF (COD_PRODUTO, COD_COSIF, COD_CLASSIFICACAO, STA_STATUS) KEY (COD_PRODUTO, COD_COSIF) VALUES ('0001', '81120000002', 'DESPES', 'A');
A7: 0002 | B7: 41520000003 | C7: PASSIV | D7: A | E7: LCI e uma divida do banco com o cliente | F7: data.sql | G7: =IF(A7="","",IFERROR(INDEX(Produtos!$B$5:$B$23,MATCH(A7,Produtos!$A$5:$A$23,0)),"Produto nao cadastrado")) -> LCI | H7: =IF(B7="","",IFERROR(VLOOKUP(LEFT(B7,1),Grupos_COSIF!$A$5:$B$12,2,FALSE()),"Outro")) -> Passivo circulante e exigivel a longo prazo | I7: =IF(B7="","",B7&" - ("&TRIM(C7)&")") -> 41520000003 - (PASSIV) | J7: =IF(B7="","",IF(COUNTIF($B$5:$B$37,B7)>1,"Sim","Nao")) -> Nao | K7: =IF(A7="","",IF(G7="Produto nao cadastrado","Cadastre o produto antes",IF(COUNTIFS($A$5:$A$37,A7,$B$5:$B$37,B7)>1,"Par duplicado",IF(AND(LEN(A7)=4,LEN(B7)=11,LEN(C7)<=6,OR(D7="A",D7="I")),"OK","Verificar tamanhos/status")))) -> OK | L7: =IF(A7="","","MERGE INTO PRODUTO_COSIF (COD_PRODUTO, COD_COSIF, COD_CLASSIFICACAO, STA_STATUS) KEY (COD_PRODUTO, COD_COSIF) VALUES ('"&A7&"', '"&B7&"', '"&C7&"', '"&D7&"');") -> MERGE INTO PRODUTO_COSIF (COD_PRODUTO, COD_COSIF, COD_CLASSIFICACAO, STA_STATUS) KEY (COD_PRODUTO, COD_COSIF) VALUES ('0002', '41520000003', 'PASSIV', 'A');
A8: 0003 | B8: 16120000004 | C8: ATIVO | D8: A | E8: Emprestimo concedido e um direito do banco | F8: data.sql | G8: =IF(A8="","",IFERROR(INDEX(Produtos!$B$5:$B$23,MATCH(A8,Produtos!$A$5:$A$23,0)),"Produto nao cadastrado")) -> Emprestimo Consignado | H8: =IF(B8="","",IFERROR(VLOOKUP(LEFT(B8,1),Grupos_COSIF!$A$5:$B$12,2,FALSE()),"Outro")) -> Ativo circulante e realizavel a longo prazo | I8: =IF(B8="","",B8&" - ("&TRIM(C8)&")") -> 16120000004 - (ATIVO) | J8: =IF(B8="","",IF(COUNTIF($B$5:$B$37,B8)>1,"Sim","Nao")) -> Nao | K8: =IF(A8="","",IF(G8="Produto nao cadastrado","Cadastre o produto antes",IF(COUNTIFS($A$5:$A$37,A8,$B$5:$B$37,B8)>1,"Par duplicado",IF(AND(LEN(A8)=4,LEN(B8)=11,LEN(C8)<=6,OR(D8="A",D8="I")),"OK","Verificar tamanhos/status")))) -> OK | L8: =IF(A8="","","MERGE INTO PRODUTO_COSIF (COD_PRODUTO, COD_COSIF, COD_CLASSIFICACAO, STA_STATUS) KEY (COD_PRODUTO, COD_COSIF) VALUES ('"&A8&"', '"&B8&"', '"&C8&"', '"&D8&"');") -> MERGE INTO PRODUTO_COSIF (COD_PRODUTO, COD_COSIF, COD_CLASSIFICACAO, STA_STATUS) KEY (COD_PRODUTO, COD_COSIF) VALUES ('0003', '16120000004', 'ATIVO', 'A');
A9: 0003 | B9: 71110000005 | C9: RECEIT | D9: A | E9: Juros que o banco recebe no emprestimo | F9: data.sql | G9: =IF(A9="","",IFERROR(INDEX(Produtos!$B$5:$B$23,MATCH(A9,Produtos!$A$5:$A$23,0)),"Produto nao cadastrado")) -> Emprestimo Consignado | H9: =IF(B9="","",IFERROR(VLOOKUP(LEFT(B9,1),Grupos_COSIF!$A$5:$B$12,2,FALSE()),"Outro")) -> Contas de resultado credoras (receitas) | I9: =IF(B9="","",B9&" - ("&TRIM(C9)&")") -> 71110000005 - (RECEIT) | J9: =IF(B9="","",IF(COUNTIF($B$5:$B$37,B9)>1,"Sim","Nao")) -> Sim | K9: =IF(A9="","",IF(G9="Produto nao cadastrado","Cadastre o produto antes",IF(COUNTIFS($A$5:$A$37,A9,$B$5:$B$37,B9)>1,"Par duplicado",IF(AND(LEN(A9)=4,LEN(B9)=11,LEN(C9)<=6,OR(D9="A",D9="I")),"OK","Verificar tamanhos/status")))) -> OK | L9: =IF(A9="","","MERGE INTO PRODUTO_COSIF (COD_PRODUTO, COD_COSIF, COD_CLASSIFICACAO, STA_STATUS) KEY (COD_PRODUTO, COD_COSIF) VALUES ('"&A9&"', '"&B9&"', '"&C9&"', '"&D9&"');") -> MERGE INTO PRODUTO_COSIF (COD_PRODUTO, COD_COSIF, COD_CLASSIFICACAO, STA_STATUS) KEY (COD_PRODUTO, COD_COSIF) VALUES ('0003', '71110000005', 'RECEIT', 'A');
A10: 0004 | B10: 18810000006 | C10: ATIVO | D10: A | E10: Direito do banco na operacao de cambio | F10: data.sql | G10: =IF(A10="","",IFERROR(INDEX(Produtos!$B$5:$B$23,MATCH(A10,Produtos!$A$5:$A$23,0)),"Produto nao cadastrado")) -> Cambio Pronto | H10: =IF(B10="","",IFERROR(VLOOKUP(LEFT(B10,1),Grupos_COSIF!$A$5:$B$12,2,FALSE()),"Outro")) -> Ativo circulante e realizavel a longo prazo | I10: =IF(B10="","",B10&" - ("&TRIM(C10)&")") -> 18810000006 - (ATIVO) | J10: =IF(B10="","",IF(COUNTIF($B$5:$B$37,B10)>1,"Sim","Nao")) -> Nao | K10: =IF(A10="","",IF(G10="Produto nao cadastrado","Cadastre o produto antes",IF(COUNTIFS($A$5:$A$37,A10,$B$5:$B$37,B10)>1,"Par duplicado",IF(AND(LEN(A10)=4,LEN(B10)=11,LEN(C10)<=6,OR(D10="A",D10="I")),"OK","Verificar tamanhos/status")))) -> OK | L10: =IF(A10="","","MERGE INTO PRODUTO_COSIF (COD_PRODUTO, COD_COSIF, COD_CLASSIFICACAO, STA_STATUS) KEY (COD_PRODUTO, COD_COSIF) VALUES ('"&A10&"', '"&B10&"', '"&C10&"', '"&D10&"');") -> MERGE INTO PRODUTO_COSIF (COD_PRODUTO, COD_COSIF, COD_CLASSIFICACAO, STA_STATUS) KEY (COD_PRODUTO, COD_COSIF) VALUES ('0004', '18810000006', 'ATIVO', 'A');
A11: 0004 | B11: 71810000007 | C11: RECEIT | D11: A | E11: Receita da operacao de cambio | F11: data.sql | G11: =IF(A11="","",IFERROR(INDEX(Produtos!$B$5:$B$23,MATCH(A11,Produtos!$A$5:$A$23,0)),"Produto nao cadastrado")) -> Cambio Pronto | H11: =IF(B11="","",IFERROR(VLOOKUP(LEFT(B11,1),Grupos_COSIF!$A$5:$B$12,2,FALSE()),"Outro")) -> Contas de resultado credoras (receitas) | I11: =IF(B11="","",B11&" - ("&TRIM(C11)&")") -> 71810000007 - (RECEIT) | J11: =IF(B11="","",IF(COUNTIF($B$5:$B$37,B11)>1,"Sim","Nao")) -> Nao | K11: =IF(A11="","",IF(G11="Produto nao cadastrado","Cadastre o produto antes",IF(COUNTIFS($A$5:$A$37,A11,$B$5:$B$37,B11)>1,"Par duplicado",IF(AND(LEN(A11)=4,LEN(B11)=11,LEN(C11)<=6,OR(D11="A",D11="I")),"OK","Verificar tamanhos/status")))) -> OK | L11: =IF(A11="","","MERGE INTO PRODUTO_COSIF (COD_PRODUTO, COD_COSIF, COD_CLASSIFICACAO, STA_STATUS) KEY (COD_PRODUTO, COD_COSIF) VALUES ('"&A11&"', '"&B11&"', '"&C11&"', '"&D11&"');") -> MERGE INTO PRODUTO_COSIF (COD_PRODUTO, COD_COSIF, COD_CLASSIFICACAO, STA_STATUS) KEY (COD_PRODUTO, COD_COSIF) VALUES ('0004', '71810000007', 'RECEIT', 'A');
A12: 0006 | B12: 41200000010 | C12: PASSIV | D12: A | E12: Depositos de poupanca: o dinheiro e do cliente | F12: script 07 | G12: =IF(A12="","",IFERROR(INDEX(Produtos!$B$5:$B$23,MATCH(A12,Produtos!$A$5:$A$23,0)),"Produto nao cadastrado")) -> Poupanca | H12: =IF(B12="","",IFERROR(VLOOKUP(LEFT(B12,1),Grupos_COSIF!$A$5:$B$12,2,FALSE()),"Outro")) -> Passivo circulante e exigivel a longo prazo | I12: =IF(B12="","",B12&" - ("&TRIM(C12)&")") -> 41200000010 - (PASSIV) | J12: =IF(B12="","",IF(COUNTIF($B$5:$B$37,B12)>1,"Sim","Nao")) -> Nao | K12: =IF(A12="","",IF(G12="Produto nao cadastrado","Cadastre o produto antes",IF(COUNTIFS($A$5:$A$37,A12,$B$5:$B$37,B12)>1,"Par duplicado",IF(AND(LEN(A12)=4,LEN(B12)=11,LEN(C12)<=6,OR(D12="A",D12="I")),"OK","Verificar tamanhos/status")))) -> OK | L12: =IF(A12="","","MERGE INTO PRODUTO_COSIF (COD_PRODUTO, COD_COSIF, COD_CLASSIFICACAO, STA_STATUS) KEY (COD_PRODUTO, COD_COSIF) VALUES ('"&A12&"', '"&B12&"', '"&C12&"', '"&D12&"');") -> MERGE INTO PRODUTO_COSIF (COD_PRODUTO, COD_COSIF, COD_CLASSIFICACAO, STA_STATUS) KEY (COD_PRODUTO, COD_COSIF) VALUES ('0006', '41200000010', 'PASSIV', 'A');
A13: 0006 | B13: 81130000011 | C13: DESPES | D13: A | E13: Rendimento pago ao cliente da poupanca | F13: script 07 | G13: =IF(A13="","",IFERROR(INDEX(Produtos!$B$5:$B$23,MATCH(A13,Produtos!$A$5:$A$23,0)),"Produto nao cadastrado")) -> Poupanca | H13: =IF(B13="","",IFERROR(VLOOKUP(LEFT(B13,1),Grupos_COSIF!$A$5:$B$12,2,FALSE()),"Outro")) -> Contas de resultado devedoras (despesas) | I13: =IF(B13="","",B13&" - ("&TRIM(C13)&")") -> 81130000011 - (DESPES) | J13: =IF(B13="","",IF(COUNTIF($B$5:$B$37,B13)>1,"Sim","Nao")) -> Nao | K13: =IF(A13="","",IF(G13="Produto nao cadastrado","Cadastre o produto antes",IF(COUNTIFS($A$5:$A$37,A13,$B$5:$B$37,B13)>1,"Par duplicado",IF(AND(LEN(A13)=4,LEN(B13)=11,LEN(C13)<=6,OR(D13="A",D13="I")),"OK","Verificar tamanhos/status")))) -> OK | L13: =IF(A13="","","MERGE INTO PRODUTO_COSIF (COD_PRODUTO, COD_COSIF, COD_CLASSIFICACAO, STA_STATUS) KEY (COD_PRODUTO, COD_COSIF) VALUES ('"&A13&"', '"&B13&"', '"&C13&"', '"&D13&"');") -> MERGE INTO PRODUTO_COSIF (COD_PRODUTO, COD_COSIF, COD_CLASSIFICACAO, STA_STATUS) KEY (COD_PRODUTO, COD_COSIF) VALUES ('0006', '81130000011', 'DESPES', 'A');
A14: 0007 | B14: 41110000012 | C14: PASSIV | D14: A | E14: Depositos a vista: saldo do cliente | F14: script 07 | G14: =IF(A14="","",IFERROR(INDEX(Produtos!$B$5:$B$23,MATCH(A14,Produtos!$A$5:$A$23,0)),"Produto nao cadastrado")) -> Conta Corrente | H14: =IF(B14="","",IFERROR(VLOOKUP(LEFT(B14,1),Grupos_COSIF!$A$5:$B$12,2,FALSE()),"Outro")) -> Passivo circulante e exigivel a longo prazo | I14: =IF(B14="","",B14&" - ("&TRIM(C14)&")") -> 41110000012 - (PASSIV) | J14: =IF(B14="","",IF(COUNTIF($B$5:$B$37,B14)>1,"Sim","Nao")) -> Nao | K14: =IF(A14="","",IF(G14="Produto nao cadastrado","Cadastre o produto antes",IF(COUNTIFS($A$5:$A$37,A14,$B$5:$B$37,B14)>1,"Par duplicado",IF(AND(LEN(A14)=4,LEN(B14)=11,LEN(C14)<=6,OR(D14="A",D14="I")),"OK","Verificar tamanhos/status")))) -> OK | L14: =IF(A14="","","MERGE INTO PRODUTO_COSIF (COD_PRODUTO, COD_COSIF, COD_CLASSIFICACAO, STA_STATUS) KEY (COD_PRODUTO, COD_COSIF) VALUES ('"&A14&"', '"&B14&"', '"&C14&"', '"&D14&"');") -> MERGE INTO PRODUTO_COSIF (COD_PRODUTO, COD_COSIF, COD_CLASSIFICACAO, STA_STATUS) KEY (COD_PRODUTO, COD_COSIF) VALUES ('0007', '41110000012', 'PASSIV', 'A');
A15: 0007 | B15: 71790000013 | C15: RECEIT | D15: A | E15: Tarifas cobradas na conta | F15: script 07 | G15: =IF(A15="","",IFERROR(INDEX(Produtos!$B$5:$B$23,MATCH(A15,Produtos!$A$5:$A$23,0)),"Produto nao cadastrado")) -> Conta Corrente | H15: =IF(B15="","",IFERROR(VLOOKUP(LEFT(B15,1),Grupos_COSIF!$A$5:$B$12,2,FALSE()),"Outro")) -> Contas de resultado credoras (receitas) | I15: =IF(B15="","",B15&" - ("&TRIM(C15)&")") -> 71790000013 - (RECEIT) | J15: =IF(B15="","",IF(COUNTIF($B$5:$B$37,B15)>1,"Sim","Nao")) -> Nao | K15: =IF(A15="","",IF(G15="Produto nao cadastrado","Cadastre o produto antes",IF(COUNTIFS($A$5:$A$37,A15,$B$5:$B$37,B15)>1,"Par duplicado",IF(AND(LEN(A15)=4,LEN(B15)=11,LEN(C15)<=6,OR(D15="A",D15="I")),"OK","Verificar tamanhos/status")))) -> OK | L15: =IF(A15="","","MERGE INTO PRODUTO_COSIF (COD_PRODUTO, COD_COSIF, COD_CLASSIFICACAO, STA_STATUS) KEY (COD_PRODUTO, COD_COSIF) VALUES ('"&A15&"', '"&B15&"', '"&C15&"', '"&D15&"');") -> MERGE INTO PRODUTO_COSIF (COD_PRODUTO, COD_COSIF, COD_CLASSIFICACAO, STA_STATUS) KEY (COD_PRODUTO, COD_COSIF) VALUES ('0007', '71790000013', 'RECEIT', 'A');
A16: 0008 | B16: 16110000014 | C16: ATIVO | D16: A | E16: Valor emprestado a pessoa fisica (direito do banco) | F16: script 07 | G16: =IF(A16="","",IFERROR(INDEX(Produtos!$B$5:$B$23,MATCH(A16,Produtos!$A$5:$A$23,0)),"Produto nao cadastrado")) -> Credito Pessoal | H16: =IF(B16="","",IFERROR(VLOOKUP(LEFT(B16,1),Grupos_COSIF!$A$5:$B$12,2,FALSE()),"Outro")) -> Ativo circulante e realizavel a longo prazo | I16: =IF(B16="","",B16&" - ("&TRIM(C16)&")") -> 16110000014 - (ATIVO) | J16: =IF(B16="","",IF(COUNTIF($B$5:$B$37,B16)>1,"Sim","Nao")) -> Nao | K16: =IF(A16="","",IF(G16="Produto nao cadastrado","Cadastre o produto antes",IF(COUNTIFS($A$5:$A$37,A16,$B$5:$B$37,B16)>1,"Par duplicado",IF(AND(LEN(A16)=4,LEN(B16)=11,LEN(C16)<=6,OR(D16="A",D16="I")),"OK","Verificar tamanhos/status")))) -> OK | L16: =IF(A16="","","MERGE INTO PRODUTO_COSIF (COD_PRODUTO, COD_COSIF, COD_CLASSIFICACAO, STA_STATUS) KEY (COD_PRODUTO, COD_COSIF) VALUES ('"&A16&"', '"&B16&"', '"&C16&"', '"&D16&"');") -> MERGE INTO PRODUTO_COSIF (COD_PRODUTO, COD_COSIF, COD_CLASSIFICACAO, STA_STATUS) KEY (COD_PRODUTO, COD_COSIF) VALUES ('0008', '16110000014', 'ATIVO', 'A');
... A22: 0001 | B22: 49910000019 | C22: PASSIV | D22: A | E22: Impostos a recolher (IOF/IR): conta nova em produto existente | F22: script 07 | G22: =IF(A22="","",IFERROR(INDEX(Produtos!$B$5:$B$23,MATCH(A22,Produtos!$A$5:$A$23,0)),"Produto nao cadastrado")) -> CDB Pos-Fixado | H22: =IF(B22="","",IFERROR(VLOOKUP(LEFT(B22,1),Grupos_COSIF!$A$5:$B$12,2,FALSE()),"Outro")) -> Passivo circulante e exigivel a longo prazo | I22: =IF(B22="","",B22&" - ("&TRIM(C22)&")") -> 49910000019 - (PASSIV) | J22: =IF(B22="","",IF(COUNTIF($B$5:$B$37,B22)>1,"Sim","Nao")) -> Nao | K22: =IF(A22="","",IF(G22="Produto nao cadastrado","Cadastre o produto antes",IF(COUNTIFS($A$5:$A$37,A22,$B$5:$B$37,B22)>1,"Par duplicado",IF(AND(LEN(A22)=4,LEN(B22)=11,LEN(C22)<=6,OR(D22="A",D22="I")),"OK","Verificar tamanhos/status")))) -> OK | L22: =IF(A22="","","MERGE INTO PRODUTO_COSIF (COD_PRODUTO, COD_COSIF, COD_CLASSIFICACAO, STA_STATUS) KEY (COD_PRODUTO, COD_COSIF) VALUES ('"&A22&"', '"&B22&"', '"&C22&"', '"&D22&"');") -> MERGE INTO PRODUTO_COSIF (COD_PRODUTO, COD_COSIF, COD_CLASSIFICACAO, STA_STATUS) KEY (COD_PRODUTO, COD_COSIF) VALUES ('0001', '49910000019', 'PASSIV', 'A');
G23: =IF(A23="","",IFERROR(INDEX(Produtos!$B$5:$B$23,MATCH(A23,Produtos!$A$5:$A$23,0)),"Produto nao cadastrado")) | H23: =IF(B23="","",IFERROR(VLOOKUP(LEFT(B23,1),Grupos_COSIF!$A$5:$B$12,2,FALSE()),"Outro")) | I23: =IF(B23="","",B23&" - ("&TRIM(C23)&")") | J23: =IF(B23="","",IF(COUNTIF($B$5:$B$37,B23)>1,"Sim","Nao")) | K23: =IF(A23="","",IF(G23="Produto nao cadastrado","Cadastre o produto antes",IF(COUNTIFS($A$5:$A$37,A23,$B$5:$B$37,B23)>1,"Par duplicado",IF(AND(LEN(A23)=4,LEN(B23)=11,LEN(C23)<=6,OR(D23="A",D23="I")),"OK","Verificar tamanhos/status")))) | L23: =IF(A23="","","MERGE INTO PRODUTO_COSIF (COD_PRODUTO, COD_COSIF, COD_CLASSIFICACAO, STA_STATUS) KEY (COD_PRODUTO, COD_COSIF) VALUES ('"&A23&"', '"&B23&"', '"&C23&"', '"&D23&"');")
G24: =IF(A24="","",IFERROR(INDEX(Produtos!$B$5:$B$23,MATCH(A24,Produtos!$A$5:$A$23,0)),"Produto nao cadastrado")) | H24: =IF(B24="","",IFERROR(VLOOKUP(LEFT(B24,1),Grupos_COSIF!$A$5:$B$12,2,FALSE()),"Outro")) | I24: =IF(B24="","",B24&" - ("&TRIM(C24)&")") | J24: =IF(B24="","",IF(COUNTIF($B$5:$B$37,B24)>1,"Sim","Nao")) | K24: =IF(A24="","",IF(G24="Produto nao cadastrado","Cadastre o produto antes",IF(COUNTIFS($A$5:$A$37,A24,$B$5:$B$37,B24)>1,"Par duplicado",IF(AND(LEN(A24)=4,LEN(B24)=11,LEN(C24)<=6,OR(D24="A",D24="I")),"OK","Verificar tamanhos/status")))) | L24: =IF(A24="","","MERGE INTO PRODUTO_COSIF (COD_PRODUTO, COD_COSIF, COD_CLASSIFICACAO, STA_STATUS) KEY (COD_PRODUTO, COD_COSIF) VALUES ('"&A24&"', '"&B24&"', '"&C24&"', '"&D24&"');")
G25: =IF(A25="","",IFERROR(INDEX(Produtos!$B$5:$B$23,MATCH(A25,Produtos!$A$5:$A$23,0)),"Produto nao cadastrado")) | H25: =IF(B25="","",IFERROR(VLOOKUP(LEFT(B25,1),Grupos_COSIF!$A$5:$B$12,2,FALSE()),"Outro")) | I25: =IF(B25="","",B25&" - ("&TRIM(C25)&")") | J25: =IF(B25="","",IF(COUNTIF($B$5:$B$37,B25)>1,"Sim","Nao")) | K25: =IF(A25="","",IF(G25="Produto nao cadastrado","Cadastre o produto antes",IF(COUNTIFS($A$5:$A$37,A25,$B$5:$B$37,B25)>1,"Par duplicado",IF(AND(LEN(A25)=4,LEN(B25)=11,LEN(C25)<=6,OR(D25="A",D25="I")),"OK","Verificar tamanhos/status")))) | L25: =IF(A25="","","MERGE INTO PRODUTO_COSIF (COD_PRODUTO, COD_COSIF, COD_CLASSIFICACAO, STA_STATUS) KEY (COD_PRODUTO, COD_COSIF) VALUES ('"&A25&"', '"&B25&"', '"&C25&"', '"&D25&"');")
G26: =IF(A26="","",IFERROR(INDEX(Produtos!$B$5:$B$23,MATCH(A26,Produtos!$A$5:$A$23,0)),"Produto nao cadastrado")) | H26: =IF(B26="","",IFERROR(VLOOKUP(LEFT(B26,1),Grupos_COSIF!$A$5:$B$12,2,FALSE()),"Outro")) | I26: =IF(B26="","",B26&" - ("&TRIM(C26)&")") | J26: =IF(B26="","",IF(COUNTIF($B$5:$B$37,B26)>1,"Sim","Nao")) | K26: =IF(A26="","",IF(G26="Produto nao cadastrado","Cadastre o produto antes",IF(COUNTIFS($A$5:$A$37,A26,$B$5:$B$37,B26)>1,"Par duplicado",IF(AND(LEN(A26)=4,LEN(B26)=11,LEN(C26)<=6,OR(D26="A",D26="I")),"OK","Verificar tamanhos/status")))) | L26: =IF(A26="","","MERGE INTO PRODUTO_COSIF (COD_PRODUTO, COD_COSIF, COD_CLASSIFICACAO, STA_STATUS) KEY (COD_PRODUTO, COD_COSIF) VALUES ('"&A26&"', '"&B26&"', '"&C26&"', '"&D26&"');")
G27: =IF(A27="","",IFERROR(INDEX(Produtos!$B$5:$B$23,MATCH(A27,Produtos!$A$5:$A$23,0)),"Produto nao cadastrado")) | H27: =IF(B27="","",IFERROR(VLOOKUP(LEFT(B27,1),Grupos_COSIF!$A$5:$B$12,2,FALSE()),"Outro")) | I27: =IF(B27="","",B27&" - ("&TRIM(C27)&")") | J27: =IF(B27="","",IF(COUNTIF($B$5:$B$37,B27)>1,"Sim","Nao")) | K27: =IF(A27="","",IF(G27="Produto nao cadastrado","Cadastre o produto antes",IF(COUNTIFS($A$5:$A$37,A27,$B$5:$B$37,B27)>1,"Par duplicado",IF(AND(LEN(A27)=4,LEN(B27)=11,LEN(C27)<=6,OR(D27="A",D27="I")),"OK","Verificar tamanhos/status")))) | L27: =IF(A27="","","MERGE INTO PRODUTO_COSIF (COD_PRODUTO, COD_COSIF, COD_CLASSIFICACAO, STA_STATUS) KEY (COD_PRODUTO, COD_COSIF) VALUES ('"&A27&"', '"&B27&"', '"&C27&"', '"&D27&"');")
G28: =IF(A28="","",IFERROR(INDEX(Produtos!$B$5:$B$23,MATCH(A28,Produtos!$A$5:$A$23,0)),"Produto nao cadastrado")) | H28: =IF(B28="","",IFERROR(VLOOKUP(LEFT(B28,1),Grupos_COSIF!$A$5:$B$12,2,FALSE()),"Outro")) | I28: =IF(B28="","",B28&" - ("&TRIM(C28)&")") | J28: =IF(B28="","",IF(COUNTIF($B$5:$B$37,B28)>1,"Sim","Nao")) | K28: =IF(A28="","",IF(G28="Produto nao cadastrado","Cadastre o produto antes",IF(COUNTIFS($A$5:$A$37,A28,$B$5:$B$37,B28)>1,"Par duplicado",IF(AND(LEN(A28)=4,LEN(B28)=11,LEN(C28)<=6,OR(D28="A",D28="I")),"OK","Verificar tamanhos/status")))) | L28: =IF(A28="","","MERGE INTO PRODUTO_COSIF (COD_PRODUTO, COD_COSIF, COD_CLASSIFICACAO, STA_STATUS) KEY (COD_PRODUTO, COD_COSIF) VALUES ('"&A28&"', '"&B28&"', '"&C28&"', '"&D28&"');")
G29: =IF(A29="","",IFERROR(INDEX(Produtos!$B$5:$B$23,MATCH(A29,Produtos!$A$5:$A$23,0)),"Produto nao cadastrado")) | H29: =IF(B29="","",IFERROR(VLOOKUP(LEFT(B29,1),Grupos_COSIF!$A$5:$B$12,2,FALSE()),"Outro")) | I29: =IF(B29="","",B29&" - ("&TRIM(C29)&")") | J29: =IF(B29="","",IF(COUNTIF($B$5:$B$37,B29)>1,"Sim","Nao")) | K29: =IF(A29="","",IF(G29="Produto nao cadastrado","Cadastre o produto antes",IF(COUNTIFS($A$5:$A$37,A29,$B$5:$B$37,B29)>1,"Par duplicado",IF(AND(LEN(A29)=4,LEN(B29)=11,LEN(C29)<=6,OR(D29="A",D29="I")),"OK","Verificar tamanhos/status")))) | L29: =IF(A29="","","MERGE INTO PRODUTO_COSIF (COD_PRODUTO, COD_COSIF, COD_CLASSIFICACAO, STA_STATUS) KEY (COD_PRODUTO, COD_COSIF) VALUES ('"&A29&"', '"&B29&"', '"&C29&"', '"&D29&"');")
G30: =IF(A30="","",IFERROR(INDEX(Produtos!$B$5:$B$23,MATCH(A30,Produtos!$A$5:$A$23,0)),"Produto nao cadastrado")) | H30: =IF(B30="","",IFERROR(VLOOKUP(LEFT(B30,1),Grupos_COSIF!$A$5:$B$12,2,FALSE()),"Outro")) | I30: =IF(B30="","",B30&" - ("&TRIM(C30)&")") | J30: =IF(B30="","",IF(COUNTIF($B$5:$B$37,B30)>1,"Sim","Nao")) | K30: =IF(A30="","",IF(G30="Produto nao cadastrado","Cadastre o produto antes",IF(COUNTIFS($A$5:$A$37,A30,$B$5:$B$37,B30)>1,"Par duplicado",IF(AND(LEN(A30)=4,LEN(B30)=11,LEN(C30)<=6,OR(D30="A",D30="I")),"OK","Verificar tamanhos/status")))) | L30: =IF(A30="","","MERGE INTO PRODUTO_COSIF (COD_PRODUTO, COD_COSIF, COD_CLASSIFICACAO, STA_STATUS) KEY (COD_PRODUTO, COD_COSIF) VALUES ('"&A30&"', '"&B30&"', '"&C30&"', '"&D30&"');")
G31: =IF(A31="","",IFERROR(INDEX(Produtos!$B$5:$B$23,MATCH(A31,Produtos!$A$5:$A$23,0)),"Produto nao cadastrado")) | H31: =IF(B31="","",IFERROR(VLOOKUP(LEFT(B31,1),Grupos_COSIF!$A$5:$B$12,2,FALSE()),"Outro")) | I31: =IF(B31="","",B31&" - ("&TRIM(C31)&")") | J31: =IF(B31="","",IF(COUNTIF($B$5:$B$37,B31)>1,"Sim","Nao")) | K31: =IF(A31="","",IF(G31="Produto nao cadastrado","Cadastre o produto antes",IF(COUNTIFS($A$5:$A$37,A31,$B$5:$B$37,B31)>1,"Par duplicado",IF(AND(LEN(A31)=4,LEN(B31)=11,LEN(C31)<=6,OR(D31="A",D31="I")),"OK","Verificar tamanhos/status")))) | L31: =IF(A31="","","MERGE INTO PRODUTO_COSIF (COD_PRODUTO, COD_COSIF, COD_CLASSIFICACAO, STA_STATUS) KEY (COD_PRODUTO, COD_COSIF) VALUES ('"&A31&"', '"&B31&"', '"&C31&"', '"&D31&"');")
G32: =IF(A32="","",IFERROR(INDEX(Produtos!$B$5:$B$23,MATCH(A32,Produtos!$A$5:$A$23,0)),"Produto nao cadastrado")) | H32: =IF(B32="","",IFERROR(VLOOKUP(LEFT(B32,1),Grupos_COSIF!$A$5:$B$12,2,FALSE()),"Outro")) | I32: =IF(B32="","",B32&" - ("&TRIM(C32)&")") | J32: =IF(B32="","",IF(COUNTIF($B$5:$B$37,B32)>1,"Sim","Nao")) | K32: =IF(A32="","",IF(G32="Produto nao cadastrado","Cadastre o produto antes",IF(COUNTIFS($A$5:$A$37,A32,$B$5:$B$37,B32)>1,"Par duplicado",IF(AND(LEN(A32)=4,LEN(B32)=11,LEN(C32)<=6,OR(D32="A",D32="I")),"OK","Verificar tamanhos/status")))) | L32: =IF(A32="","","MERGE INTO PRODUTO_COSIF (COD_PRODUTO, COD_COSIF, COD_CLASSIFICACAO, STA_STATUS) KEY (COD_PRODUTO, COD_COSIF) VALUES ('"&A32&"', '"&B32&"', '"&C32&"', '"&D32&"');")
G33: =IF(A33="","",IFERROR(INDEX(Produtos!$B$5:$B$23,MATCH(A33,Produtos!$A$5:$A$23,0)),"Produto nao cadastrado")) | H33: =IF(B33="","",IFERROR(VLOOKUP(LEFT(B33,1),Grupos_COSIF!$A$5:$B$12,2,FALSE()),"Outro")) | I33: =IF(B33="","",B33&" - ("&TRIM(C33)&")") | J33: =IF(B33="","",IF(COUNTIF($B$5:$B$37,B33)>1,"Sim","Nao")) | K33: =IF(A33="","",IF(G33="Produto nao cadastrado","Cadastre o produto antes",IF(COUNTIFS($A$5:$A$37,A33,$B$5:$B$37,B33)>1,"Par duplicado",IF(AND(LEN(A33)=4,LEN(B33)=11,LEN(C33)<=6,OR(D33="A",D33="I")),"OK","Verificar tamanhos/status")))) | L33: =IF(A33="","","MERGE INTO PRODUTO_COSIF (COD_PRODUTO, COD_COSIF, COD_CLASSIFICACAO, STA_STATUS) KEY (COD_PRODUTO, COD_COSIF) VALUES ('"&A33&"', '"&B33&"', '"&C33&"', '"&D33&"');")
G34: =IF(A34="","",IFERROR(INDEX(Produtos!$B$5:$B$23,MATCH(A34,Produtos!$A$5:$A$23,0)),"Produto nao cadastrado")) | H34: =IF(B34="","",IFERROR(VLOOKUP(LEFT(B34,1),Grupos_COSIF!$A$5:$B$12,2,FALSE()),"Outro")) | I34: =IF(B34="","",B34&" - ("&TRIM(C34)&")") | J34: =IF(B34="","",IF(COUNTIF($B$5:$B$37,B34)>1,"Sim","Nao")) | K34: =IF(A34="","",IF(G34="Produto nao cadastrado","Cadastre o produto antes",IF(COUNTIFS($A$5:$A$37,A34,$B$5:$B$37,B34)>1,"Par duplicado",IF(AND(LEN(A34)=4,LEN(B34)=11,LEN(C34)<=6,OR(D34="A",D34="I")),"OK","Verificar tamanhos/status")))) | L34: =IF(A34="","","MERGE INTO PRODUTO_COSIF (COD_PRODUTO, COD_COSIF, COD_CLASSIFICACAO, STA_STATUS) KEY (COD_PRODUTO, COD_COSIF) VALUES ('"&A34&"', '"&B34&"', '"&C34&"', '"&D34&"');")
... G37: =IF(A37="","",IFERROR(INDEX(Produtos!$B$5:$B$23,MATCH(A37,Produtos!$A$5:$A$23,0)),"Produto nao cadastrado")) | H37: =IF(B37="","",IFERROR(VLOOKUP(LEFT(B37,1),Grupos_COSIF!$A$5:$B$12,2,FALSE()),"Outro")) | I37: =IF(B37="","",B37&" - ("&TRIM(C37)&")") | J37: =IF(B37="","",IF(COUNTIF($B$5:$B$37,B37)>1,"Sim","Nao")) | K37: =IF(A37="","",IF(G37="Produto nao cadastrado","Cadastre o produto antes",IF(COUNTIFS($A$5:$A$37,A37,$B$5:$B$37,B37)>1,"Par duplicado",IF(AND(LEN(A37)=4,LEN(B37)=11,LEN(C37)<=6,OR(D37="A",D37="I")),"OK","Verificar tamanhos/status")))) | L37: =IF(A37="","","MERGE INTO PRODUTO_COSIF (COD_PRODUTO, COD_COSIF, COD_CLASSIFICACAO, STA_STATUS) KEY (COD_PRODUTO, COD_COSIF) VALUES ('"&A37&"', '"&B37&"', '"&C37&"', '"&D37&"');")

Sheet Grupos_COSIF
A1: Grupos do plano COSIF (1º dígito do código)
A2: Tabela de apoio usada pela coluna "Grupo COSIF" da aba Produtos_Cosif.
A4: 1º dígito | B4: Grupo | C4: Exemplo de uso
A5: 1 | B5: Ativo circulante e realizavel a longo prazo | C5: Emprestimos concedidos
A6: 2 | B6: Ativo permanente | C6: Imoveis e investimentos do banco
A7: 3 | B7: Compensacao (ativo) | C7: Controles fora do balanco
A8: 4 | B8: Passivo circulante e exigivel a longo prazo | C8: Depositos, CDB, LCI, impostos a recolher
A9: 6 | B9: Patrimonio liquido | C9: Capital social
A10: 7 | B10: Contas de resultado credoras (receitas) | C10: Juros recebidos, tarifas
A11: 8 | B11: Contas de resultado devedoras (despesas) | C11: Juros pagos, rendimento da poupanca
A12: 9 | B12: Compensacao (passivo) | C12: Controles fora do balanco
